[
  {
    "date": "2026-07-01",
    "iv_30d": 0.6117
  },
  {
    "date": "2026-07-01",
    "iv_30d": 0.6117
  },
  {
    "date": "2026-07-01",
    "iv_30d": 0.7119
  },
  {
    "date": "2026-07-01",
    "iv_30d": 0.6042
  },
  {
    "date": "2026-07-01",
    "iv_30d": 0.7265
  },
  {
    "date": "2026-07-01",
    "iv_30d": 0.6196
  },
  {
    "date": "2026-07-01",
    "iv_30d": 0.5673
  },
  {
    "date": "2026-07-01",
    "iv_30d": 0.7015
  },
  {
    "date": "2026-07-01",
    "iv_30d": 0.6045
  },
  {
    "date": "2026-07-01",
    "iv_30d": 0.607
  },
  {
    "date": "2026-07-01",
    "iv_30d": 0.6462
  },
  {
    "date": "2026-07-01",
    "iv_30d": 0.6218
  },
  {
    "date": "2026-07-01",
    "iv_30d": 0.6002
  },
  {
    "date": "2026-07-01",
    "iv_30d": 0.5703
  },
  {
    "date": "2026-07-01",
    "iv_30d": 0.5669
  },
  {
    "date": "2026-07-02",
    "iv_30d": 0.605
  },
  {
    "date": "2026-07-02",
    "iv_30d": 0.6773
  },
  {
    "date": "2026-07-02",
    "iv_30d": 0.7058
  },
  {
    "date": "2026-07-02",
    "iv_30d": 0.7058
  },
  {
    "date": "2026-07-02",
    "iv_30d": 0.7058
  },
  {
    "date": "2026-07-02",
    "iv_30d": 0.7058
  },
  {
    "date": "2026-07-02",
    "iv_30d": 0.6783
  },
  {
    "date": "2026-07-02",
    "iv_30d": 0.6112
  },
  {
    "date": "2026-07-02",
    "iv_30d": 0.6421
  },
  {
    "date": "2026-07-02",
    "iv_30d": 0.7078
  },
  {
    "date": "2026-07-02",
    "iv_30d": 0.6039
  },
  {
    "date": "2026-07-02",
    "iv_30d": 0.7071
  },
  {
    "date": "2026-07-02",
    "iv_30d": 0.6032
  },
  {
    "date": "2026-07-02",
    "iv_30d": 0.6649
  },
  {
    "date": "2026-07-02",
    "iv_30d": 0.6632
  },
  {
    "date": "2026-07-02",
    "iv_30d": 0.6649
  },
  {
    "date": "2026-07-02",
    "iv_30d": 0.5987
  },
  {
    "date": "2026-07-02",
    "iv_30d": 0.6579
  },
  {
    "date": "2026-07-02",
    "iv_30d": 0.639
  },
  {
    "date": "2026-07-02",
    "iv_30d": 0.7383
  },
  {
    "date": "2026-07-02",
    "iv_30d": 0.6792
  },
  {
    "date": "2026-07-02",
    "iv_30d": 0.5487
  },
  {
    "date": "2026-07-02",
    "iv_30d": 0.7001
  },
  {
    "date": "2026-07-02",
    "iv_30d": 0.7132
  },
  {
    "date": "2026-07-02",
    "iv_30d": 0.5901
  },
  {
    "date": "2026-07-02",
    "iv_30d": 0.6191
  },
  {
    "date": "2026-07-02",
    "iv_30d": 0.683
  },
  {
    "date": "2026-07-02",
    "iv_30d": 0.6919
  },
  {
    "date": "2026-07-02",
    "iv_30d": 0.6926
  },
  {
    "date": "2026-07-02",
    "iv_30d": 0.6262
  },
  {
    "date": "2026-07-02",
    "iv_30d": 0.6747
  },
  {
    "date": "2026-07-02",
    "iv_30d": 0.5499
  },
  {
    "date": "2026-07-03",
    "iv_30d": 0.6037
  },
  {
    "date": "2026-07-03",
    "iv_30d": 0.6037
  },
  {
    "date": "2026-07-03",
    "iv_30d": 0.6037
  },
  {
    "date": "2026-07-03",
    "iv_30d": 0.6037
  },
  {
    "date": "2026-07-03",
    "iv_30d": 0.6037
  },
  {
    "date": "2026-07-03",
    "iv_30d": 0.6037
  },
  {
    "date": "2026-07-03",
    "iv_30d": 0.6037
  },
  {
    "date": "2026-07-03",
    "iv_30d": 0.6037
  },
  {
    "date": "2026-07-03",
    "iv_30d": 0.6037
  },
  {
    "date": "2026-07-03",
    "iv_30d": 0.6037
  },
  {
    "date": "2026-07-03",
    "iv_30d": 0.6037
  },
  {
    "date": "2026-07-03",
    "iv_30d": 0.6037
  },
  {
    "date": "2026-07-03",
    "iv_30d": 0.6037
  },
  {
    "date": "2026-07-03",
    "iv_30d": 0.6037
  },
  {
    "date": "2026-07-03",
    "iv_30d": 0.6037
  },
  {
    "date": "2026-07-03",
    "iv_30d": 0.6037
  },
  {
    "date": "2026-07-03",
    "iv_30d": 0.6037
  },
  {
    "date": "2026-07-03",
    "iv_30d": 0.6037
  },
  {
    "date": "2026-07-03",
    "iv_30d": 0.6037
  },
  {
    "date": "2026-07-03",
    "iv_30d": 0.6037
  },
  {
    "date": "2026-07-03",
    "iv_30d": 0.6037
  },
  {
    "date": "2026-07-03",
    "iv_30d": 0.6037
  },
  {
    "date": "2026-07-03",
    "iv_30d": 0.6037
  },
  {
    "date": "2026-07-03",
    "iv_30d": 0.6037
  },
  {
    "date": "2026-07-03",
    "iv_30d": 0.6037
  },
  {
    "date": "2026-07-03",
    "iv_30d": 0.6037
  },
  {
    "date": "2026-07-03",
    "iv_30d": 0.6037
  },
  {
    "date": "2026-07-03",
    "iv_30d": 0.6037
  },
  {
    "date": "2026-07-03",
    "iv_30d": 0.6037
  },
  {
    "date": "2026-07-03",
    "iv_30d": 0.6037
  },
  {
    "date": "2026-07-03",
    "iv_30d": 0.6037
  },
  {
    "date": "2026-07-03",
    "iv_30d": 0.6037
  },
  {
    "date": "2026-07-06",
    "iv_30d": 0.7592
  },
  {
    "date": "2026-07-06",
    "iv_30d": 0.7592
  },
  {
    "date": "2026-07-06",
    "iv_30d": 0.7592
  },
  {
    "date": "2026-07-06",
    "iv_30d": 0.7592
  },
  {
    "date": "2026-07-06",
    "iv_30d": 0.7592
  },
  {
    "date": "2026-07-06",
    "iv_30d": 0.6507
  },
  {
    "date": "2026-07-06",
    "iv_30d": 0.6507
  },
  {
    "date": "2026-07-06",
    "iv_30d": 0.7557
  },
  {
    "date": "2026-07-06",
    "iv_30d": 0.6905
  },
  {
    "date": "2026-07-06",
    "iv_30d": 0.6915
  },
  {
    "date": "2026-07-06",
    "iv_30d": 0.58
  },
  {
    "date": "2026-07-06",
    "iv_30d": 0.7517
  },
  {
    "date": "2026-07-06",
    "iv_30d": 0.7514
  }
]