{
  "timestamp": "2026-06-14T05:00:16.576755",
  "data": {
    "COIN": {
      "composite": {
        "bullish": 42,
        "bearish": 58,
        "volume": 500,
        "source": "fallback-neutral",
        "timestamp": "2026-06-14T05:00:02.983356"
      },
      "fallback": {
        "bullish": 42,
        "bearish": 58,
        "volume": 500,
        "source": "fallback-neutral",
        "timestamp": "2026-06-14T05:00:02.983356"
      }
    },
    "DKNG": {
      "composite": {
        "bullish": 55,
        "bearish": 45,
        "volume": 400,
        "source": "fallback",
        "timestamp": "2026-06-14T05:00:03.842072"
      },
      "fallback": {
        "bullish": 55,
        "bearish": 45,
        "volume": 400,
        "source": "fallback",
        "timestamp": "2026-06-14T05:00:03.842072"
      }
    },
    "NET": {
      "composite": {
        "bullish": 45,
        "bearish": 55,
        "volume": 400,
        "source": "fallback",
        "timestamp": "2026-06-14T05:00:04.566698"
      },
      "fallback": {
        "bullish": 45,
        "bearish": 55,
        "volume": 400,
        "source": "fallback",
        "timestamp": "2026-06-14T05:00:04.566698"
      }
    },
    "PATH": {
      "composite": {
        "bullish": 49,
        "bearish": 51,
        "volume": 540,
        "source": "fallback",
        "timestamp": "2026-06-14T05:00:05.267162"
      },
      "fallback": {
        "bullish": 49,
        "bearish": 51,
        "volume": 540,
        "source": "fallback",
        "timestamp": "2026-06-14T05:00:05.267162"
      }
    },
    "SHOP": {
      "composite": {
        "bullish": 70,
        "bearish": 30,
        "volume": 655,
        "source": "fallback",
        "timestamp": "2026-06-14T05:00:05.998185"
      },
      "fallback": {
        "bullish": 70,
        "bearish": 30,
        "volume": 655,
        "source": "fallback",
        "timestamp": "2026-06-14T05:00:05.998185"
      }
    },
    "SQ": {
      "composite": {
        "bullish": 60,
        "bearish": 40,
        "volume": 434,
        "source": "fallback",
        "timestamp": "2026-06-14T05:00:06.675551"
      },
      "fallback": {
        "bullish": 60,
        "bearish": 40,
        "volume": 434,
        "source": "fallback",
        "timestamp": "2026-06-14T05:00:06.675551"
      }
    },
    "SQQQ": {
      "composite": {
        "bullish": 28,
        "bearish": 72,
        "volume": 1200,
        "source": "fallback-bearish",
        "timestamp": "2026-06-14T05:00:07.458290"
      },
      "fallback": {
        "bullish": 28,
        "bearish": 72,
        "volume": 1200,
        "source": "fallback-bearish",
        "timestamp": "2026-06-14T05:00:07.458290"
      }
    },
    "TQQQ": {
      "composite": {
        "bullish": 72,
        "bearish": 28,
        "volume": 1400,
        "source": "fallback-bullish",
        "timestamp": "2026-06-14T05:00:08.200147"
      },
      "fallback": {
        "bullish": 72,
        "bearish": 28,
        "volume": 1400,
        "source": "fallback-bullish",
        "timestamp": "2026-06-14T05:00:08.200147"
      }
    },
    "UPST": {
      "composite": {
        "bullish": 52,
        "bearish": 48,
        "volume": 460,
        "source": "fallback",
        "timestamp": "2026-06-14T05:00:08.934927"
      },
      "fallback": {
        "bullish": 52,
        "bearish": 48,
        "volume": 460,
        "source": "fallback",
        "timestamp": "2026-06-14T05:00:08.934927"
      }
    },
    "XLE": {
      "composite": {
        "bullish": 55,
        "bearish": 45,
        "volume": 400,
        "source": "fallback",
        "timestamp": "2026-06-14T05:00:09.691417"
      },
      "fallback": {
        "bullish": 55,
        "bearish": 45,
        "volume": 400,
        "source": "fallback",
        "timestamp": "2026-06-14T05:00:09.691417"
      }
    },
    "AMZN": {
      "composite": {
        "bullish": 55,
        "bearish": 45,
        "volume": 400,
        "source": "fallback",
        "timestamp": "2026-06-14T05:00:10.342235"
      },
      "fallback": {
        "bullish": 55,
        "bearish": 45,
        "volume": 400,
        "source": "fallback",
        "timestamp": "2026-06-14T05:00:10.342235"
      }
    },
    "NFLX": {
      "composite": {
        "bullish": 55,
        "bearish": 45,
        "volume": 400,
        "source": "fallback",
        "timestamp": "2026-06-14T05:00:11.002351"
      },
      "fallback": {
        "bullish": 55,
        "bearish": 45,
        "volume": 400,
        "source": "fallback",
        "timestamp": "2026-06-14T05:00:11.002351"
      }
    },
    "SNOW": {
      "composite": {
        "bullish": 55,
        "bearish": 45,
        "volume": 422,
        "source": "fallback",
        "timestamp": "2026-06-14T05:00:11.654081"
      },
      "fallback": {
        "bullish": 55,
        "bearish": 45,
        "volume": 422,
        "source": "fallback",
        "timestamp": "2026-06-14T05:00:11.654081"
      }
    },
    "SOFI": {
      "composite": {
        "bullish": 55,
        "bearish": 45,
        "volume": 400,
        "source": "fallback",
        "timestamp": "2026-06-14T05:00:12.310299"
      },
      "fallback": {
        "bullish": 55,
        "bearish": 45,
        "volume": 400,
        "source": "fallback",
        "timestamp": "2026-06-14T05:00:12.310299"
      }
    },
    "CDNS": {
      "composite": {
        "bullish": 55,
        "bearish": 45,
        "volume": 400,
        "source": "fallback",
        "timestamp": "2026-06-14T05:00:13.028968"
      },
      "fallback": {
        "bullish": 55,
        "bearish": 45,
        "volume": 400,
        "source": "fallback",
        "timestamp": "2026-06-14T05:00:13.028968"
      }
    },
    "LCID": {
      "composite": {
        "bullish": 55,
        "bearish": 45,
        "volume": 400,
        "source": "fallback",
        "timestamp": "2026-06-14T05:00:13.731196"
      },
      "fallback": {
        "bullish": 55,
        "bearish": 45,
        "volume": 400,
        "source": "fallback",
        "timestamp": "2026-06-14T05:00:13.731196"
      }
    },
    "NIO": {
      "composite": {
        "bullish": 55,
        "bearish": 45,
        "volume": 400,
        "source": "fallback",
        "timestamp": "2026-06-14T05:00:14.444575"
      },
      "fallback": {
        "bullish": 55,
        "bearish": 45,
        "volume": 400,
        "source": "fallback",
        "timestamp": "2026-06-14T05:00:14.444575"
      }
    },
    "XPEV": {
      "composite": {
        "bullish": 55,
        "bearish": 45,
        "volume": 400,
        "source": "fallback",
        "timestamp": "2026-06-14T05:00:15.173947"
      },
      "fallback": {
        "bullish": 55,
        "bearish": 45,
        "volume": 400,
        "source": "fallback",
        "timestamp": "2026-06-14T05:00:15.173947"
      }
    },
    "GM": {
      "composite": {
        "bullish": 55,
        "bearish": 45,
        "volume": 400,
        "source": "fallback",
        "timestamp": "2026-06-14T05:00:15.913526"
      },
      "fallback": {
        "bullish": 55,
        "bearish": 45,
        "volume": 400,
        "source": "fallback",
        "timestamp": "2026-06-14T05:00:15.913526"
      }
    },
    "ABNB": {
      "composite": {
        "bullish": 55,
        "bearish": 45,
        "volume": 400,
        "source": "fallback",
        "timestamp": "2026-06-14T05:00:16.576347"
      },
      "fallback": {
        "bullish": 55,
        "bearish": 45,
        "volume": 400,
        "source": "fallback",
        "timestamp": "2026-06-14T05:00:16.576347"
      }
    }
  },
  "symbol_count": 20,
  "sources": [
    "stocktwits",
    "fallback"
  ]
}